pipomatic.py
pipomatic-4.2.dist-info/LICENSE
pipomatic-4.2.dist-info/METADATA
pipomatic-4.2.dist-info/WHEEL
pipomatic-4.2.dist-info/entry_points.txt
pipomatic-4.2.dist-info/top_level.txt
pipomatic-4.2.dist-info/RECORD
