Metadata-Version: 2.1
Name: pipomatic
Version: 4.2
Summary: Automating the creation of an installable PIP module from a Jupyter notebook
Home-page: https://github.com/eq8r/pipomatic
Author: eq8r
Author-email: doug.hudgeon@eq8r.com
License: UNKNOWN
Platform: UNKNOWN
Classifier: Programming Language :: Python :: 3
Classifier: License :: OSI Approved :: MIT License
Classifier: Operating System :: OS Independent
Requires-Dist: black
Requires-Dist: click
Requires-Dist: ipython
Requires-Dist: nbformat
Requires-Dist: nbconvert
Requires-Dist: setuptools
Requires-Dist: twine
Requires-Dist: wheel
